codeshield/cs.py
codeshield/insecure_code_detector/README.md
codeshield/insecure_code_detector/analyzers.py
codeshield/insecure_code_detector/insecure_code_detector.py
codeshield/insecure_code_detector/insecure_patterns.py
codeshield/insecure_code_detector/issues.py
codeshield/insecure_code_detector/languages.py
codeshield/insecure_code_detector/oss.py
codeshield/insecure_code_detector/usecases.py
codeshield/insecure_code_detector/rules/README.md
codeshield/insecure_code_detector/rules/config.yaml
codeshield/insecure_code_detector/rules/regex/c.yaml
codeshield/insecure_code_detector/rules/regex/cpp.yaml
codeshield/insecure_code_detector/rules/regex/csharp.yaml
codeshield/insecure_code_detector/rules/regex/hack.yaml
codeshield/insecure_code_detector/rules/regex/java.yaml
codeshield/insecure_code_detector/rules/regex/javascript.yaml
codeshield/insecure_code_detector/rules/regex/language_agnostic.yaml
codeshield/insecure_code_detector/rules/regex/objective_c.yaml
codeshield/insecure_code_detector/rules/regex/php.yaml
codeshield/insecure_code_detector/rules/regex/python.yaml
codeshield/insecure_code_detector/rules/regex/ruby.yaml
codeshield/insecure_code_detector/rules/regex/rules.rs
codeshield/insecure_code_detector/rules/regex/rust.yaml
codeshield/insecure_code_detector/rules/regex/swift.yaml
codeshield/insecure_code_detector/rules/regex/xml.yaml
codeshield/insecure_code_detector/rules/semgrep/_generated_/c_codeshield.json
codeshield/insecure_code_detector/rules/semgrep/_generated_/c_cyberseceval.json
codeshield/insecure_code_detector/rules/semgrep/_generated_/cpp_codeshield.json
codeshield/insecure_code_detector/rules/semgrep/_generated_/cpp_cyberseceval.json
codeshield/insecure_code_detector/rules/semgrep/_generated_/csharp_codeshield.json
codeshield/insecure_code_detector/rules/semgrep/_generated_/csharp_cyberseceval.json
codeshield/insecure_code_detector/rules/semgrep/_generated_/java_codeshield.json
codeshield-1.0.0.dist-info/METADATA
codeshield-1.0.0.dist-info/WHEEL
codeshield-1.0.0.dist-info/licenses/LICENSE
codeshield-1.0.0.dist-info/RECORD
