Metadata-Version: 2.3
Name: codeshield
Version: 1.0.0
Summary: Shield against LLM generated insecure code
Project-URL: Homepage, https://github.com/meta-llama/PurpleLlama
Project-URL: Issues, https://github.com/meta-llama/PurpleLlama/issues
Author-email: Sahana CB <csahana@meta.com>, Thomas Robinson <trobinson@meta.com>
License-File: LICENSE
Classifier: License :: OSI Approved :: MIT License
Classifier: Operating System :: OS Independent
Classifier: Programming Language :: Python :: 3
Requires-Python: >=3.8
Requires-Dist: pyyaml
Requires-Dist: semgrep>1.68
Provides-Extra: external-llm
Requires-Dist: llama-recipes; extra == 'external-llm'
